[
  {
    "id": "danielJoseph",
    "name": "Daniel Joseph",
    "productionTimeBoost": 0.5,
    "experienceBoost": 0.1,
    "productionCostBoost": 0.1,
    "quantityBoost": 0,
    "worksCount": 20,
    "hireCost": 20
  },

  {
    "id": "roseDixon",
    "name": "Rose Dixon",
    "productionTimeBoost": 0.1,
    "experienceBoost": 0,
    "productionCostBoost": 0.1,
    "quantityBoost": 0.5,
    "worksCount": 20,
    "hireCost": 20000
  },

  {
    "id": "thomasJack",
    "name": "Thomas Jack",
    "productionTimeBoost": 0.3,
    "experienceBoost": 0.1,
    "productionCostBoost": 0.1,
    "quantityBoost": 0.3,
    "worksCount": 20,
    "hireCost": 40000
  },

  {
    "id": "poppyStewart",
    "name": "Poppy Stewart",
    "productionTimeBoost": 0.1,
    "experienceBoost": 0.1,
    "productionCostBoost": 0.3,
    "quantityBoost": 0.3,
    "worksCount": 20,
    "hireCost": 40000
  },

  {
    "id": "harryLewis",
    "name": "Harry Lewis",
    "productionTimeBoost": 0.6,
    "experienceBoost": 0.1,
    "productionCostBoost": 0.3,
    "quantityBoost": 0.4,
    "worksCount": 30,
    "hireCost": 80000
  },

  {
    "id": "elenaCole",
    "name": "Elena Cole",
    "productionTimeBoost": 0.3,
    "experienceBoost": 0.1,
    "productionCostBoost": 0.4,
    "quantityBoost": 0.6,
    "worksCount": 30,
    "hireCost": 80000
  }
]
